MANIFEST.in
README.rst
cnlp.c
setup.cfg
setup.py
primed/__init__.py
primed/nlp.py
primed/utilities.py
primed.egg-info/PKG-INFO
primed.egg-info/SOURCES.txt
primed.egg-info/dependency_links.txt
primed.egg-info/not-zip-safe
primed.egg-info/requires.txt
primed.egg-info/top_level.txt
primed/data/__init__.py
primed/data/cmudict.dict