Metadata-Version: 1.2
Name: primed
Version: 0.9
Summary: The Primed Toolkit
Home-page: https://github.com/eyb1/primed
Author: Eugene Bann, Primed
Author-email: eugene@primed.one
License: Apache 2
Platform: UNKNOWN
Requires-Python: >=3.4
